sweepy/__init__.py
sweepy/game.py
sweepy/logic.py
sweepy/ouija.py
sweepy_tui-0.1.5.dist-info/METADATA
sweepy_tui-0.1.5.dist-info/WHEEL
sweepy_tui-0.1.5.dist-info/entry_points.txt
sweepy_tui-0.1.5.dist-info/top_level.txt
sweepy_tui-0.1.5.dist-info/RECORD
